[{"stateMutability": "nonpayable", "type": "function", "name": "register_music", "inputs": [{"name": "title", "type": "string"}], "outputs": []}, {"stateMutability": "payable", "type": "function", "name": "pay_and_distribute", "inputs": [{"name": "music_id", "type": "uint256"}], "outputs": []}, {"stateMutability": "view", "type": "function", "name": "music_registry", "inputs": [{"name": "arg0", "type": "uint256"}], "outputs": [{"name": "", "type": "tuple", "components": [{"name": "title", "type": "string"}, {"name": "artist", "type": "address"}, {"name": "exists", "type": "bool"}]}]}, {"stateMutability": "view", "type": "function", "name": "music_hashes", "inputs": [{"name": "arg0", "type": "bytes32"}], "outputs": [{"name": "", "type": "bool"}]}, {"stateMutability": "view", "type": "function", "name": "next_music_id", "inputs": [], "outputs": [{"name": "", "type": "uint256"}]}]